<annotation>
    <folder>VOC2007</folder>
    <filename>people(6880).jpg</filename>
<source>
<database>orgaquant</database>
<annotation>organoids</annotation>
</source>
    <size>
        <width>500</width>
        <height>332</height>
        <depth>3</depth>
    </size>
            <segmented>0</segmented>
    <object>
<name>falling</name>
                    <pose>Unspecified</pose>
                    <truncated>0</truncated>
                    <difficult>0</difficult>
        <bndbox>
            <xmin>276</xmin>
            <ymin>99</ymin>
            <xmax>506</xmax>
            <ymax>202</ymax>
        </bndbox>
    </object>
</annotation>