<annotation>
    <folder>VOC2007</folder>
    <filename>people(7167).jpg</filename>
<source>
<database>orgaquant</database>
<annotation>organoids</annotation>
</source>
    <size>
        <width>499</width>
        <height>331</height>
        <depth>3</depth>
    </size>
            <segmented>0</segmented>
    <object>
<name>falling</name>
                    <pose>Unspecified</pose>
                    <truncated>0</truncated>
                    <difficult>0</difficult>
        <bndbox>
            <xmin>19</xmin>
            <ymin>167</ymin>
            <xmax>479</xmax>
            <ymax>260</ymax>
        </bndbox>
    </object>
</annotation>